Metadata-Version: 1.0
Name: matrix-calculator
Version: 0.1.1
Summary: Matrix Calculator
Home-page: UNKNOWN
Author: UNKNOWN
Author-email: UNKNOWN
License: UNKNOWN
Platform: UNKNOWN
